bridge/__init__.py
bridge/main.py
bridge/util.py
backend_bridge-1.4.0.dist-info/LICENSE
backend_bridge-1.4.0.dist-info/METADATA
backend_bridge-1.4.0.dist-info/WHEEL
backend_bridge-1.4.0.dist-info/top_level.txt
backend_bridge-1.4.0.dist-info/RECORD
