Metadata-Version: 2.1
Name: backend-bridge
Version: 1.4.0
Summary: 注册并代理转发后端服务
License-File: LICENSE
Requires-Dist: requests-toolbelt
